simpysql/DBModel.py
simpysql/__init__.py
simpysql/Connections/CassandraConnection.py
simpysql/Connections/CassandraConnectionpool.py
simpysql/Connections/Connection.py
simpysql/Connections/ConnectionFactory.py
simpysql/Connections/MongoConnection.py
simpysql/Connections/MysqlConnection.py
simpysql/Connections/MysqlConnectionpool.py
simpysql/Connections/PostgresConnection.py
simpysql/Connections/PostgresConnectionpool.py
simpysql/Connections/SqlServerConnection.py
simpysql/Connections/__init__.py
simpysql/Eloquent/BaseBuilder.py
simpysql/Eloquent/BuilderFactory.py
simpysql/Eloquent/CassandraBuilder.py
simpysql/Eloquent/MongoBuilder.py
simpysql/Eloquent/MysqlBuilder.py
simpysql/Eloquent/MysqlBuilder_back.py
simpysql/Eloquent/PostgresBuilder.py
simpysql/Eloquent/SqlServerBuilder.py
simpysql/Eloquent/__init__.py
simpysql/Util/Config.py
simpysql/Util/Dynamic.py
simpysql/Util/Expression.py
simpysql/Util/Logger.py
simpysql/Util/MagicMetaClass.py
simpysql/Util/Response.py
simpysql/Util/__init__.py
simpysqls-0.5.15.dist-info/licenses/LICENSE
simpysqls-0.5.15.dist-info/METADATA
simpysqls-0.5.15.dist-info/WHEEL
simpysqls-0.5.15.dist-info/entry_points.txt
simpysqls-0.5.15.dist-info/top_level.txt
simpysqls-0.5.15.dist-info/RECORD
