Metadata-Version: 2.4
Name: simpysqls
Version: 0.5.15
Summary: A simple mysql orm base on pymysql
Home-page: 
Author: jeanku, liubin
Author-email: 
Keywords: MySQL ORM
Classifier: Programming Language :: Python :: 3
Classifier: License :: OSI Approved :: MIT License
Classifier: Operating System :: OS Independent
Requires-Python: >=3
License-File: LICENSE
Requires-Dist: pymysql
Requires-Dist: pandas
Requires-Dist: configparser
Requires-Dist: DBUtils
Requires-Dist: pymongo
Dynamic: author
Dynamic: classifier
Dynamic: description
Dynamic: description-content-type
Dynamic: keywords
Dynamic: license-file
Dynamic: requires-dist
Dynamic: requires-python
Dynamic: summary
